django_freeradius/__init__.py
django_freeradius/admin.py
django_freeradius/apps.py
django_freeradius/models.py
django_freeradius/settings.py
django_freeradius/urls.py
django_freeradius/utils.py
django_freeradius/api/__init__.py
django_freeradius/api/serializers.py
django_freeradius/api/urls.py
django_freeradius/api/views.py
django_freeradius/base/__init__.py
django_freeradius/base/admin.py
django_freeradius/base/admin_actions.py
django_freeradius/base/admin_filters.py
django_freeradius/base/forms.py
django_freeradius/base/models.py
django_freeradius/base/validators.py
django_freeradius/management/__init__.py
django_freeradius/management/commands/__init__.py
django_freeradius/management/commands/batch_add_users.py
django_freeradius/management/commands/cleanup_stale_radacct.py
django_freeradius/management/commands/deactivate_expired_users.py
django_freeradius/management/commands/delete_old_postauth.py
django_freeradius/management/commands/delete_old_radacct.py
django_freeradius/management/commands/delete_old_users.py
django_freeradius/management/commands/prefix_add_users.py
django_freeradius/management/commands/base/__init__.py
django_freeradius/management/commands/base/batch_add_users.py
django_freeradius/management/commands/base/cleanup_stale_radacct.py
django_freeradius/management/commands/base/deactivate_expired_users.py
django_freeradius/management/commands/base/delete_old_postauth.py
django_freeradius/management/commands/base/delete_old_radacct.py
django_freeradius/management/commands/base/delete_old_users.py
django_freeradius/management/commands/base/prefix_add_users.py
django_freeradius/migrations/0001_initial_freeradius.py
django_freeradius/migrations/0002_add_customizations.py
django_freeradius/migrations/0003_default_radius_groups.py
django_freeradius/migrations/0004_radiustoken.py
django_freeradius/migrations/0005_add_radactt_fields.py
django_freeradius/migrations/__init__.py
django_freeradius/social/__init__.py
django_freeradius/social/views.py
django_freeradius-0.1.dist-info/LICENSE
django_freeradius-0.1.dist-info/METADATA
django_freeradius-0.1.dist-info/WHEEL
django_freeradius-0.1.dist-info/top_level.txt
django_freeradius-0.1.dist-info/RECORD
